src/__init__.py
src/chromedriver_manager.py
src/test_chromedriver_manager.py
SimpleChromeDriverManager-1.0.0.dist-info/LICENSE
SimpleChromeDriverManager-1.0.0.dist-info/METADATA
SimpleChromeDriverManager-1.0.0.dist-info/WHEEL
SimpleChromeDriverManager-1.0.0.dist-info/top_level.txt
SimpleChromeDriverManager-1.0.0.dist-info/RECORD
