Metadata-Version: 2.1
Name: SimpleChromeDriverManager
Version: 1.0.0
Summary: Chromedriver Manager is a Python library that automates the download and installation of the latest version of Chromedriver, making it easier to set up environments for Robotic Process Automation (RPA) applications. Ideal for developers using Selenium or other tools that require Chromedriver, this package ensures that you always have the correct version, eliminating compatibility issues between the browser and the driver.
Home-page: https://github.com/fnmanfre/ChromeDriverManager
Author: Fernando N. Manfre
Author-email: fn.manfre@gmail.com
Classifier: License :: OSI Approved :: MIT License
Classifier: Programming Language :: Python :: 3
Classifier: Programming Language :: Python :: 3.10
Classifier: Programming Language :: Python :: 3.11
Classifier: Operating System :: Microsoft :: Windows :: Windows 10
Classifier: Operating System :: Microsoft :: Windows :: Windows 11
Classifier: Operating System :: OS Independent
Requires-Python: >=3.10
License-File: LICENSE
Requires-Dist: certifi==2024.7.4
Requires-Dist: charset-normalizer==3.3.2
Requires-Dist: idna==3.7
Requires-Dist: requests==2.32.3
Requires-Dist: urllib3==2.2.2
